notification/__init__.py
notification/abstractNotifyTemplate.py
notification/dingTalk.py
notification/template.py
pipilong_notify-0.2.0.dist-info/METADATA
pipilong_notify-0.2.0.dist-info/WHEEL
pipilong_notify-0.2.0.dist-info/top_level.txt
pipilong_notify-0.2.0.dist-info/RECORD
